miko/__info__.py
miko/__init__.py
miko/__main__.py
miko/miko.py
miko/parser/__init__.py
miko/parser/example.py
miko/parser/list.py
miko/parser/parser.py
miko-1.1.dist-info/LICENSE
miko-1.1.dist-info/METADATA
miko-1.1.dist-info/WHEEL
miko-1.1.dist-info/entry_points.txt
miko-1.1.dist-info/RECORD
