Metadata-Version: 2.1
Name: miko
Version: 1.1
Summary: See how to use a Python object at a glance!
Home-page: https://github.com/Animenosekai/miko
License: MIT
Keywords: animenosekai,miko,docs,documentation,parser
Author: Animenosekai
Author-email: animenosekai.mail@gmail.com
Maintainer: Animenosekai
Maintainer-email: animenosekai.mail@gmail.com
Requires-Python: >=3.6,<4.0
Classifier: Development Status :: 4 - Beta
Classifier: Environment :: Console
Classifier: Intended Audience :: Developers
Classifier: License :: OSI Approved :: MIT License
Classifier: Operating System :: OS Independent
Classifier: Programming Language :: Python
Classifier: Programming Language :: Python :: 3
Classifier: Programming Language :: Python :: 3.6
Classifier: Programming Language :: Python :: 3.7
Classifier: Programming Language :: Python :: 3.8
Classifier: Programming Language :: Python :: 3.9
Classifier: Programming Language :: Python :: 3.10
Classifier: Programming Language :: Python :: 3.11
Classifier: Topic :: Documentation
Classifier: Topic :: Software Development :: Documentation
Classifier: Typing :: Typed
Project-URL: Documentation, https://github.com/Animenosekai/miko/blob/main/README.md
Project-URL: Issue Tracker, https://github.com/Animenosekai/miko/issues
Project-URL: Repository, https://github.com/Animenosekai/miko
